ArgusEX1/Poc.csv
ArgusEX1/__inti__.py
ArgusEX1/ramdon_pokemon.py
ArgusEX1/random_pokemon.py
ArgusEX1-2.0.2.dist-info/METADATA
ArgusEX1-2.0.2.dist-info/WHEEL
ArgusEX1-2.0.2.dist-info/top_level.txt
ArgusEX1-2.0.2.dist-info/RECORD
