Metadata-Version: 2.1
Name: ArgusEX1
Version: 2.0.2
Summary: Libreria para generar un pokemin aleatoriamento
Author: JMEX
Author-email: kvkgif95949@gmail.com
Requires-Dist: pandas
